univoc_tools/UnivocElasticAPI.py
univoc_tools/__init__.py
univoc_tools-0.1.1.dist-info/LICENSE
univoc_tools-0.1.1.dist-info/METADATA
univoc_tools-0.1.1.dist-info/WHEEL
univoc_tools-0.1.1.dist-info/top_level.txt
univoc_tools-0.1.1.dist-info/RECORD
