Metadata-Version: 2.1
Name: univoc-tools
Version: 0.1.1
Summary: Package created for UNIVOC Team
Home-page: UNKNOWN
Author: Prijilevschi Dumitru
License: UNKNOWN
Platform: UNKNOWN
Requires-Python: >=3.9.6
License-File: LICENSE
Requires-Dist: elasticsearch (==7.13.3)
